README.md
setup.py
genslug/__init__.py
genslug.egg-info/PKG-INFO
genslug.egg-info/SOURCES.txt
genslug.egg-info/dependency_links.txt
genslug.egg-info/top_level.txt